verilator/cpp2/counter.v
module counter(input clk,
    input reset,
    output reg [7:0] q);
    
    always @(posedge clk) begin
        if (reset)
            q <= 0;
        else
            q <= q + 1;
    end
endmodule

verilator/cpp3/divider.v
module divider(input clk,
    output clk_o);

    parameter DIV = 4;

    reg [7:0] counter = 0;

    assign clk_o = counter == DIV - 1;

    always @(posedge clk) begin
        if (counter == DIV - 1)
            counter <= 0;
        else
            counter <= counter + 1;
    end

endmodule

verilator/cpp3/top.v
module top(input clk, input reset, output reg [7:0] q);
    wire clk_o;

    divider #(5) div(.clk(clk), .clk_o(clk_o));

    counter cnt(.clk(clk_o), .reset(reset), .q(q)); 

endmodule;

verilator/cpp3/test.vcd
$version Generated by VerilatedVcd $end
$date Thu Dec 24 15:13:12 2020
 $end
$timescale   1ps $end

 $scope module TOP $end
  $var wire  1 # clk $end
  $var wire  8 % q [7:0] $end
  $var wire  1 $ reset $end
  $scope module top $end
   $var wire  1 # clk $end
   $var wire  1 & clk_o $end
   $var wire  8 % q [7:0] $end
   $var wire  1 $ reset $end
   $scope module cnt $end
    $var wire  1 & clk $end
    $var wire  8 % q [7:0] $end
    $var wire  1 $ reset $end
   $upscope $end
   $scope module div $end
    $var wire 32 ( DIV [31:0] $end
    $var wire  1 # clk $end
    $var wire  1 & clk_o $end
    $var wire  8 ' counter [7:0] $end
   $upscope $end
  $upscope $end
 $upscope $end
$enddefinitions $end


#8
0#
0$
b00000000 %
0&
b00000000 '
b00000000000000000000000000000101 (
#10
1#
b00000001 '
#15
0#
#18
#20
1#
b00000010 '
#25
0#
#28
#30
1#
b00000011 '
#35
0#
#38
#40
1#
b00000100 '
#45
0#
#48
#50
1#
b00000001 %
1&
b00000000 '
#55
0#
#58
#60
1#
0&
b00000001 '
#65
0#
#68
#70
1#
b00000010 '
#75
0#
#78
#80
1#
b00000011 '
#85
0#
#88
#90
1#
b00000100 '
#95
0#
#98
#100
1#
b00000010 %
1&
b00000000 '
#105
0#
#108
#110
1#
0&
b00000001 '
#115
0#
#118
#120
1#
b00000010 '
#125
0#
#128
#130
1#
b00000011 '
#135
0#
#138
#140
1#
b00000100 '
#145
0#
#148
#150
1#
b00000011 %
1&
b00000000 '
#155
0#
#158
#160
1#
0&
b00000001 '
#165
0#
#168
#170
1#
b00000010 '
#175
0#
#178
#180
1#
b00000011 '
#185
0#
#188
#190
1#
b00000100 '
#195
0#
#198
#200
1#
b00000100 %
1&
b00000000 '
#205
0#
#208
#210
1#
0&
b00000001 '
#215
0#
#218
#220
1#
b00000010 '
#225
0#
#228
#230
1#
b00000011 '
#235
0#
#238
#240
1#
b00000100 '
#245
0#
#248
#250
1#
b00000101 %
1&
b00000000 '
#255
0#
#258
#260
1#
0&
b00000001 '
#265
0#
#268
#270
1#
b00000010 '
#275
0#
#278
#280
1#
b00000011 '
#285
0#
#288
#290
1#
b00000100 '
#295
0#
#298
#300
1#
b00000110 %
1&
b00000000 '
#305
0#
#308
#310
1#
0&
b00000001 '
#315
0#
#318
#320
1#
b00000010 '
#325
0#
#328
#330
1#
b00000011 '
#335
0#
#338
#340
1#
b00000100 '
#345
0#
#348
#350
1#
b00000111 %
1&
b00000000 '
#355
0#
#358
#360
1#
0&
b00000001 '
#365
0#
#368
#370
1#
b00000010 '
#375
0#
#378
#380
1#
b00000011 '
#385
0#
#388
#390
1#
b00000100 '
#395
0#
#398
#400
1#
b00001000 %
1&
b00000000 '
#405
0#
#408
#410
1#
0&
b00000001 '
#415
0#
#418
#420
1#
b00000010 '
#425
0#
#428
#430
1#
b00000011 '
#435
0#
#438
#440
1#
b00000100 '
#445
0#
#448
#450
1#
b00001001 %
1&
b00000000 '
#455
0#
#458
#460
1#
0&
b00000001 '
#465
0#
#468
#470
1#
b00000010 '
#475
0#
#478
#480
1#
b00000011 '
#485
0#
#488
#490
1#
b00000100 '
#495
0#
#498
#500
1#
b00001010 %
1&
b00000000 '
#505
0#
#508
#510
1#
0&
b00000001 '
#515
0#
#518
#520
1#
b00000010 '
#525
0#
#528
#530
1#
b00000011 '
#535
0#
#538
#540
1#
b00000100 '
#545
0#
#548
#550
1#
b00001011 %
1&
b00000000 '
#555
0#
#558
#560
1#
0&
b00000001 '
#565
0#
#568
#570
1#
b00000010 '
#575
0#
#578
#580
1#
b00000011 '
#585
0#
#588
#590
1#
b00000100 '
#595
0#
#598
#600
1#
b00001100 %
1&
b00000000 '
#605
0#
#608
#610
1#
0&
b00000001 '
#615
0#
#618
#620
1#
b00000010 '
#625
0#
#628
#630
1#
b00000011 '
#635
0#
#638
#640
1#
b00000100 '
#645
0#
#648
#650
1#
b00001101 %
1&
b00000000 '
#655
0#
#658
#660
1#
0&
b00000001 '
#665
0#
#668
#670
1#
b00000010 '
#675
0#
#678
#680
1#
b00000011 '
#685
0#
#688
#690
1#
b00000100 '
#695
0#
#698
#700
1#
b00001110 %
1&
b00000000 '
#705
0#
#708
#710
1#
0&
b00000001 '
#715
0#
#718
#720
1#
b00000010 '
#725
0#
#728
#730
1#
b00000011 '
#735
0#
#738
#740
1#
b00000100 '
#745
0#
#748
#750
1#
b00001111 %
1&
b00000000 '
#755
0#
#758
#760
1#
0&
b00000001 '
#765
0#
#768
#770
1#
b00000010 '
#775
0#
#778
#780
1#
b00000011 '
#785
0#
#788
#790
1#
b00000100 '
#795
0#
#798
#800
1#
b00010000 %
1&
b00000000 '
#805
0#
#808
#810
1#
0&
b00000001 '
#815
0#
#818
#820
1#
b00000010 '
#825
0#
#828
#830
1#
b00000011 '
#835
0#
#838
#840
1#
b00000100 '
#845
0#
#848
#850
1#
b00010001 %
1&
b00000000 '
#855
0#
#858
#860
1#
0&
b00000001 '
#865
0#
#868
#870
1#
b00000010 '
#875
0#
#878
#880
1#
b00000011 '
#885
0#
#888
#890
1#
b00000100 '
#895
0#
#898
#900
1#
b00010010 %
1&
b00000000 '
#905
0#
#908
#910
1#
0&
b00000001 '
#915
0#
#918
#920
1#
b00000010 '
#925
0#
#928
#930
1#
b00000011 '
#935
0#
#938
#940
1#
b00000100 '
#945
0#
#948
#950
1#
b00010011 %
1&
b00000000 '
#955
0#
#958
#960
1#
0&
b00000001 '
#965
0#
#968
#970
1#
b00000010 '
#975
0#
#978
#980
1#
b00000011 '
#985
0#
#988
#990
1#
b00000100 '
#995
0#
#998
#1000
1#
b00010100 %
1&
b00000000 '
#1005
0#
#1008
#1010
1#
0&
b00000001 '
#1015
0#
#1018
#1020
1#
b00000010 '
#1025
0#
#1028
#1030
1#
b00000011 '
#1035
0#
#1038
#1040
1#
b00000100 '
#1045
0#
#1048
#1050
1#
b00010101 %
1&
b00000000 '
#1055
0#
#1058
#1060
1#
0&
b00000001 '
#1065
0#
#1068
#1070
1#
b00000010 '
#1075
0#
#1078
#1080
1#
b00000011 '
#1085
0#
#1088
#1090
1#
b00000100 '
#1095
0#
#1098
#1100
1#
b00010110 %
1&
b00000000 '
#1105
0#
#1108
#1110
1#
0&
b00000001 '
#1115
0#
#1118
#1120
1#
b00000010 '
#1125
0#
#1128
#1130
1#
b00000011 '
#1135
0#
#1138
#1140
1#
b00000100 '
#1145
0#
#1148
#1150
1#
b00010111 %
1&
b00000000 '
#1155
0#
#1158
#1160
1#
0&
b00000001 '
#1165
0#
#1168
#1170
1#
b00000010 '
#1175
0#
#1178
#1180
1#
b00000011 '
#1185
0#
#1188
#1190
1#
b00000100 '
#1195
0#
#1198
#1200
1#
b00011000 %
1&
b00000000 '
#1205
0#
#1208
#1210
1#
0&
b00000001 '
#1215
0#
#1218
#1220
1#
b00000010 '
#1225
0#
#1228
#1230
1#
b00000011 '
#1235
0#
#1238
#1240
1#
b00000100 '
#1245
0#
#1248
#1250
1#
b00011001 %
1&
b00000000 '
#1255
0#
#1258
#1260
1#
0&
b00000001 '
#1265
0#
#1268
#1270
1#
b00000010 '
#1275
0#
#1278
#1280
1#
b00000011 '
#1285
0#
#1288
#1290
1#
b00000100 '
#1295
0#
#1298
#1300
1#
b00011010 %
1&
b00000000 '
#1305
0#
#1308
#1310
1#
0&
b00000001 '
#1315
0#
#1318
#1320
1#
b00000010 '
#1325
0#
#1328
#1330
1#
b00000011 '
#1335
0#
#1338
#1340
1#
b00000100 '
#1345
0#
#1348
#1350
1#
b00011011 %
1&
b00000000 '
#1355
0#
#1358
#1360
1#
0&
b00000001 '
#1365
0#
#1368
#1370
1#
b00000010 '
#1375
0#
#1378
#1380
1#
b00000011 '
#1385
0#
#1388
#1390
1#
b00000100 '
#1395
0#
#1398
#1400
1#
b00011100 %
1&
b00000000 '
#1405
0#
#1408
#1410
1#
0&
b00000001 '
#1415
0#
#1418
#1420
1#
b00000010 '
#1425
0#
#1428
#1430
1#
b00000011 '
#1435
0#
#1438
#1440
1#
b00000100 '
#1445
0#
#1448
#1450
1#
b00011101 %
1&
b00000000 '
#1455
0#
#1458
#1460
1#
0&
b00000001 '
#1465
0#
#1468
#1470
1#
b00000010 '
#1475
0#
#1478
#1480
1#
b00000011 '
#1485
0#
#1488
#1490
1#
b00000100 '
#1495
0#
#1498
#1500
1#
b00011110 %
1&
b00000000 '
#1505
0#
#1508
#1510
1#
0&
b00000001 '
#1515
0#
#1518
#1520
1#
b00000010 '
#1525
0#
#1528
#1530
1#
b00000011 '
#1535
0#
#1538
#1540
1#
b00000100 '
#1545
0#
#1548
#1550
1#
b00011111 %
1&
b00000000 '
#1555
0#
#1558
#1560
1#
0&
b00000001 '
#1565
0#
#1568
#1570
1#
b00000010 '
#1575
0#
#1578
#1580
1#
b00000011 '
#1585
0#
#1588
#1590
1#
b00000100 '
#1595
0#
#1598
#1600
1#
b00100000 %
1&
b00000000 '
#1605
0#
#1608
#1610
1#
0&
b00000001 '
#1615
0#
#1618
#1620
1#
b00000010 '
#1625
0#
#1628
#1630
1#
b00000011 '
#1635
0#
#1638
#1640
1#
b00000100 '
#1645
0#
#1648
#1650
1#
b00100001 %
1&
b00000000 '
#1655
0#
#1658
#1660
1#
0&
b00000001 '
#1665
0#
#1668
#1670
1#
b00000010 '
#1675
0#
#1678
#1680
1#
b00000011 '
#1685
0#
#1688
#1690
1#
b00000100 '
#1695
0#
#1698
#1700
1#
b00100010 %
1&
b00000000 '
#1705
0#
#1708
#1710
1#
0&
b00000001 '
#1715
0#
#1718
#1720
1#
b00000010 '
#1725
0#
#1728
#1730
1#
b00000011 '
#1735
0#
#1738
#1740
1#
b00000100 '
#1745
0#
#1748
#1750
1#
b00100011 %
1&
b00000000 '
#1755
0#
#1758
#1760
1#
0&
b00000001 '
#1765
0#
#1768
#1770
1#
b00000010 '
#1775
0#
#1778
#1780
1#
b00000011 '
#1785
0#
#1788
#1790
1#
b00000100 '
#1795
0#
#1798
#1800
1#
b00100100 %
1&
b00000000 '
#1805
0#
#1808
#1810
1#
0&
b00000001 '
#1815
0#
#1818
#1820
1#
b00000010 '
#1825
0#
#1828
#1830
1#
b00000011 '
#1835
0#
#1838
#1840
1#
b00000100 '
#1845
0#
#1848
#1850
1#
b00100101 %
1&
b00000000 '
#1855
0#
#1858
#1860
1#
0&
b00000001 '
#1865
0#
#1868
#1870
1#
b00000010 '
#1875
0#
#1878
#1880
1#
b00000011 '
#1885
0#
#1888
#1890
1#
b00000100 '
#1895
0#
#1898
#1900
1#
b00100110 %
1&
b00000000 '
#1905
0#
#1908
#1910
1#
0&
b00000001 '
#1915
0#
#1918
#1920
1#
b00000010 '
#1925
0#
#1928
#1930
1#
b00000011 '
#1935
0#
#1938
#1940
1#
b00000100 '
#1945
0#
#1948
#1950
1#
b00100111 %
1&
b00000000 '
#1955
0#
#1958
#1960
1#
0&
b00000001 '
#1965
0#
#1968
#1970
1#
b00000010 '
#1975
0#
#1978
#1980
1#
b00000011 '
#1985
0#
#1988
#1990
1#
b00000100 '
#1995
0#
#1998
#2000
1#
b00101000 %
1&
b00000000 '
#2005
0#
#2008
#2010
1#
0&
b00000001 '
#2015
0#
#2018
#2020
1#
b00000010 '
#2025
0#
#2028
#2030
1#
b00000011 '
#2035
0#
#2038
#2040
1#
b00000100 '
#2045
0#
#2048
#2050
1#
b00101001 %
1&
b00000000 '
#2055
0#
#2058
#2060
1#
0&
b00000001 '
#2065
0#
#2068
#2070
1#
b00000010 '
#2075
0#
#2078
#2080
1#
b00000011 '
#2085
0#
#2088
#2090
1#
b00000100 '
#2095
0#
#2098
#2100
1#
b00101010 %
1&
b00000000 '
#2105
0#
#2108
#2110
1#
0&
b00000001 '
#2115
0#
#2118
#2120
1#
b00000010 '
#2125
0#
#2128
#2130
1#
b00000011 '
#2135
0#
#2138
#2140
1#
b00000100 '
#2145
0#
#2148
#2150
1#
b00101011 %
1&
b00000000 '
#2155
0#
#2158
#2160
1#
0&
b00000001 '
#2165
0#
#2168
#2170
1#
b00000010 '
#2175
0#
#2178
#2180
1#
b00000011 '
#2185
0#
#2188
#2190
1#
b00000100 '
#2195
0#
#2198
#2200
1#
b00101100 %
1&
b00000000 '
#2205
0#
#2208
#2210
1#
0&
b00000001 '
#2215
0#
#2218
#2220
1#
b00000010 '
#2225
0#
#2228
#2230
1#
b00000011 '
#2235
0#
#2238
#2240
1#
b00000100 '
#2245
0#
#2248
#2250
1#
b00101101 %
1&
b00000000 '
#2255
0#
#2258
#2260
1#
0&
b00000001 '
#2265
0#
#2268
#2270
1#
b00000010 '
#2275
0#
#2278
#2280
1#
b00000011 '
#2285
0#
#2288
#2290
1#
b00000100 '
#2295
0#
#2298
#2300
1#
b00101110 %
1&
b00000000 '
#2305
0#
#2308
#2310
1#
0&
b00000001 '
#2315
0#
#2318
#2320
1#
b00000010 '
#2325
0#
#2328
#2330
1#
b00000011 '
#2335
0#
#2338
#2340
1#
b00000100 '
#2345
0#
#2348
#2350
1#
b00101111 %
1&
b00000000 '
#2355
0#
#2358
#2360
1#
0&
b00000001 '
#2365
0#
#2368
#2370
1#
b00000010 '
#2375
0#
#2378
#2380
1#
b00000011 '
#2385
0#
#2388
#2390
1#
b00000100 '
#2395
0#
#2398
#2400
1#
b00110000 %
1&
b00000000 '
#2405
0#
#2408
#2410
1#
0&
b00000001 '
#2415
0#
#2418
#2420
1#
b00000010 '
#2425
0#
#2428
#2430
1#
b00000011 '
#2435
0#
#2438
#2440
1#
b00000100 '
#2445
0#
#2448
#2450
1#
b00110001 %
1&
b00000000 '
#2455
0#
#2458
#2460
1#
0&
b00000001 '
#2465
0#
#2468
#2470
1#
b00000010 '
#2475
0#
#2478
#2480
1#
b00000011 '
#2485
0#
#2488
#2490
1#
b00000100 '
#2495
0#
#2498
#2500
1#
b00110010 %
1&
b00000000 '
#2505
0#
#2508
#2510
1#
0&
b00000001 '
#2515
0#
#2518
#2520
1#
b00000010 '
#2525
0#
#2528
#2530
1#
b00000011 '
#2535
0#
#2538
#2540
1#
b00000100 '
#2545
0#
#2548
#2550
1#
b00110011 %
1&
b00000000 '
#2555
0#
#2558
#2560
1#
0&
b00000001 '
#2565
0#
#2568
#2570
1#
b00000010 '
#2575
0#
#2578
#2580
1#
b00000011 '
#2585
0#
#2588
#2590
1#
b00000100 '
#2595
0#
#2598
#2600
1#
b00110100 %
1&
b00000000 '
#2605
0#
#2608
#2610
1#
0&
b00000001 '
#2615
0#
#2618
#2620
1#
b00000010 '
#2625
0#
#2628
#2630
1#
b00000011 '
#2635
0#
#2638
#2640
1#
b00000100 '
#2645
0#
#2648
#2650
1#
b00110101 %
1&
b00000000 '
#2655
0#
#2658
#2660
1#
0&
b00000001 '
#2665
0#
#2668
#2670
1#
b00000010 '
#2675
0#
#2678
#2680
1#
b00000011 '
#2685
0#
#2688
#2690
1#
b00000100 '
#2695
0#
#2698
#2700
1#
b00110110 %
1&
b00000000 '
#2705
0#
#2708
#2710
1#
0&
b00000001 '
#2715
0#
#2718
#2720
1#
b00000010 '
#2725
0#
#2728
#2730
1#
b00000011 '
#2735
0#
#2738
#2740
1#
b00000100 '
#2745
0#
#2748
#2750
1#
b00110111 %
1&
b00000000 '
#2755
0#
#2758
#2760
1#
0&
b00000001 '
#2765
0#
#2768
#2770
1#
b00000010 '
#2775
0#
#2778
#2780
1#
b00000011 '
#2785
0#
#2788
#2790
1#
b00000100 '
#2795
0#
#2798
#2800
1#
b00111000 %
1&
b00000000 '
#2805
0#
#2808
#2810
1#
0&
b00000001 '
#2815
0#
#2818
#2820
1#
b00000010 '
#2825
0#
#2828
#2830
1#
b00000011 '
#2835
0#
#2838
#2840
1#
b00000100 '
#2845
0#
#2848
#2850
1#
b00111001 %
1&
b00000000 '
#2855
0#
#2858
#2860
1#
0&
b00000001 '
#2865
0#
#2868
#2870
1#
b00000010 '
#2875
0#
#2878
#2880
1#
b00000011 '
#2885
0#
#2888
#2890
1#
b00000100 '
#2895
0#
#2898
#2900
1#
b00111010 %
1&
b00000000 '
#2905
0#
#2908
#2910
1#
0&
b00000001 '
#2915
0#
#2918
#2920
1#
b00000010 '
#2925
0#
#2928
#2930
1#
b00000011 '
#2935
0#
#2938
#2940
1#
b00000100 '
#2945
0#
#2948
#2950
1#
b00111011 %
1&
b00000000 '
#2955
0#
#2958
#2960
1#
0&
b00000001 '
#2965
0#
#2968
#2970
1#
b00000010 '
#2975
0#
#2978
#2980
1#
b00000011 '
#2985
0#
#2988
#2990
1#
b00000100 '
#2995
0#
#2998
#3000
1#
b00111100 %
1&
b00000000 '
#3005
0#
#3008
#3010
1#
0&
b00000001 '
#3015
0#
#3018
#3020
1#
b00000010 '
#3025
0#
#3028
#3030
1#
b00000011 '
#3035
0#
#3038
#3040
1#
b00000100 '
#3045
0#
#3048
#3050
1#
b00111101 %
1&
b00000000 '
#3055
0#
#3058
#3060
1#
0&
b00000001 '
#3065
0#
#3068
#3070
1#
b00000010 '
#3075
0#
#3078
#3080
1#
b00000011 '
#3085
0#
#3088
#3090
1#
b00000100 '
#3095
0#
#3098
#3100
1#
b00111110 %
1&
b00000000 '
#3105
0#
#3108
#3110
1#
0&
b00000001 '
#3115
0#
#3118
#3120
1#
b00000010 '
#3125
0#
#3128
#3130
1#
b00000011 '
#3135
0#
#3138
#3140
1#
b00000100 '
#3145
0#
#3148
#3150
1#
b00111111 %
1&
b00000000 '
#3155
0#
#3158
#3160
1#
0&
b00000001 '
#3165
0#
#3168
#3170
1#
b00000010 '
#3175
0#
#3178
#3180
1#
b00000011 '
#3185
0#
#3188
#3190
1#
b00000100 '
#3195
0#
#3198
#3200
1#
b01000000 %
1&
b00000000 '
#3205
0#
#3208
#3210
1#
0&
b00000001 '
#3215
0#
#3218
#3220
1#
b00000010 '
#3225
0#
#3228
#3230
1#
b00000011 '
#3235
0#
#3238
#3240
1#
b00000100 '
#3245
0#
#3248
#3250
1#
b01000001 %
1&
b00000000 '
#3255
0#
#3258
#3260
1#
0&
b00000001 '
#3265
0#
#3268
#3270
1#
b00000010 '
#3275
0#
#3278
#3280
1#
b00000011 '
#3285
0#
#3288
#3290
1#
b00000100 '
#3295
0#
#3298
#3300
1#
b01000010 %
1&
b00000000 '
#3305
0#
#3308
#3310
1#
0&
b00000001 '
#3315
0#
#3318
#3320
1#
b00000010 '
#3325
0#
#3328
#3330
1#
b00000011 '
#3335
0#
#3338
#3340
1#
b00000100 '
#3345
0#
#3348
#3350
1#
b01000011 %
1&
b00000000 '
#3355
0#
#3358
#3360
1#
0&
b00000001 '
#3365
0#
#3368
#3370
1#
b00000010 '
#3375
0#
#3378
#3380
1#
b00000011 '
#3385
0#
#3388
#3390
1#
b00000100 '
#3395
0#
#3398
#3400
1#
b01000100 %
1&
b00000000 '
#3405
0#
#3408
#3410
1#
0&
b00000001 '
#3415
0#
#3418
#3420
1#
b00000010 '
#3425
0#
#3428
#3430
1#
b00000011 '
#3435
0#
#3438
#3440
1#
b00000100 '
#3445
0#
#3448
#3450
1#
b01000101 %
1&
b00000000 '
#3455
0#
#3458
#3460
1#
0&
b00000001 '
#3465
0#
#3468
#3470
1#
b00000010 '
#3475
0#
#3478
#3480
1#
b00000011 '
#3485
0#
#3488
#3490
1#
b00000100 '
#3495
0#
#3498
#3500
1#
b01000110 %
1&
b00000000 '
#3505
0#
#3508
#3510
1#
0&
b00000001 '
#3515
0#
#3518
#3520
1#
b00000010 '
#3525
0#
#3528
#3530
1#
b00000011 '
#3535
0#
#3538
#3540
1#
b00000100 '
#3545
0#
#3548
#3550
1#
b01000111 %
1&
b00000000 '
#3555
0#
#3558
#3560
1#
0&
b00000001 '
#3565
0#
#3568
#3570
1#
b00000010 '
#3575
0#
#3578
#3580
1#
b00000011 '
#3585
0#
#3588
#3590
1#
b00000100 '
#3595
0#
#3598
#3600
1#
b01001000 %
1&
b00000000 '
#3605
0#
#3608
#3610
1#
0&
b00000001 '
#3615
0#
#3618
#3620
1#
b00000010 '
#3625
0#
#3628
#3630
1#
b00000011 '
#3635
0#
#3638
#3640
1#
b00000100 '
#3645
0#
#3648
#3650
1#
b01001001 %
1&
b00000000 '
#3655
0#
#3658
#3660
1#
0&
b00000001 '
#3665
0#
#3668
#3670
1#
b00000010 '
#3675
0#
#3678
#3680
1#
b00000011 '
#3685
0#
#3688
#3690
1#
b00000100 '
#3695
0#
#3698
#3700
1#
b01001010 %
1&
b00000000 '
#3705
0#
#3708
#3710
1#
0&
b00000001 '
#3715
0#
#3718
#3720
1#
b00000010 '
#3725
0#
#3728
#3730
1#
b00000011 '
#3735
0#
#3738
#3740
1#
b00000100 '
#3745
0#
#3748
#3750
1#
b01001011 %
1&
b00000000 '
#3755
0#
#3758
#3760
1#
0&
b00000001 '
#3765
0#
#3768
#3770
1#
b00000010 '
#3775
0#
#3778
#3780
1#
b00000011 '
#3785
0#
#3788
#3790
1#
b00000100 '
#3795
0#
#3798
#3800
1#
b01001100 %
1&
b00000000 '
#3805
0#
#3808
#3810
1#
0&
b00000001 '
#3815
0#
#3818
#3820
1#
b00000010 '
#3825
0#
#3828
#3830
1#
b00000011 '
#3835
0#
#3838
#3840
1#
b00000100 '
#3845
0#
#3848
#3850
1#
b01001101 %
1&
b00000000 '
#3855
0#
#3858
#3860
1#
0&
b00000001 '
#3865
0#
#3868
#3870
1#
b00000010 '
#3875
0#
#3878
#3880
1#
b00000011 '
#3885
0#
#3888
#3890
1#
b00000100 '
#3895
0#
#3898
#3900
1#
b01001110 %
1&
b00000000 '
#3905
0#
#3908
#3910
1#
0&
b00000001 '
#3915
0#
#3918
#3920
1#
b00000010 '
#3925
0#
#3928
#3930
1#
b00000011 '
#3935
0#
#3938
#3940
1#
b00000100 '
#3945
0#
#3948
#3950
1#
b01001111 %
1&
b00000000 '
#3955
0#
#3958
#3960
1#
0&
b00000001 '
#3965
0#
#3968
#3970
1#
b00000010 '
#3975
0#
#3978
#3980
1#
b00000011 '
#3985
0#
#3988
#3990
1#
b00000100 '
#3995
0#
#3998
#4000
1#
b01010000 %
1&
b00000000 '
#4005
0#
#4008
#4010
1#
0&
b00000001 '
#4015
0#
#4018
#4020
1#
b00000010 '
#4025
0#
#4028
#4030
1#
b00000011 '
#4035
0#
#4038
#4040
1#
b00000100 '
#4045
0#
#4048
#4050
1#
b01010001 %
1&
b00000000 '
#4055
0#
#4058
#4060
1#
0&
b00000001 '
#4065
0#
#4068
#4070
1#
b00000010 '
#4075
0#
#4078
#4080
1#
b00000011 '
#4085
0#
#4088
#4090
1#
b00000100 '
#4095
0#
#4098
#4100
1#
b01010010 %
1&
b00000000 '
#4105
0#
#4108
#4110
1#
0&
b00000001 '
#4115
0#
#4118
#4120
1#
b00000010 '
#4125
0#
#4128
#4130
1#
b00000011 '
#4135
0#
#4138
#4140
1#
b00000100 '
#4145
0#
#4148
#4150
1#
b01010011 %
1&
b00000000 '
#4155
0#
#4158
#4160
1#
0&
b00000001 '
#4165
0#
#4168
#4170
1#
b00000010 '
#4175
0#
#4178
#4180
1#
b00000011 '
#4185
0#
#4188
#4190
1#
b00000100 '
#4195
0#
#4198
#4200
1#
b01010100 %
1&
b00000000 '
#4205
0#
#4208
#4210
1#
0&
b00000001 '
#4215
0#
#4218
#4220
1#
b00000010 '
#4225
0#
#4228
#4230
1#
b00000011 '
#4235
0#
#4238
#4240
1#
b00000100 '
#4245
0#
#4248
#4250
1#
b01010101 %
1&
b00000000 '
#4255
0#
#4258
#4260
1#
0&
b00000001 '
#4265
0#
#4268
#4270
1#
b00000010 '
#4275
0#
#4278
#4280
1#
b00000011 '
#4285
0#
#4288
#4290
1#
b00000100 '
#4295
0#
#4298
#4300
1#
b01010110 %
1&
b00000000 '
#4305
0#
#4308
#4310
1#
0&
b00000001 '
#4315
0#
#4318
#4320
1#
b00000010 '
#4325
0#
#4328
#4330
1#
b00000011 '
#4335
0#
#4338
#4340
1#
b00000100 '
#4345
0#
#4348
#4350
1#
b01010111 %
1&
b00000000 '
#4355
0#
#4358
#4360
1#
0&
b00000001 '
#4365
0#
#4368
#4370
1#
b00000010 '
#4375
0#
#4378
#4380
1#
b00000011 '
#4385
0#
#4388
#4390
1#
b00000100 '
#4395
0#
#4398
#4400
1#
b01011000 %
1&
b00000000 '
#4405
0#
#4408
#4410
1#
0&
b00000001 '
#4415
0#
#4418
#4420
1#
b00000010 '
#4425
0#
#4428
#4430
1#
b00000011 '
#4435
0#
#4438
#4440
1#
b00000100 '
#4445
0#
#4448
#4450
1#
b01011001 %
1&
b00000000 '
#4455
0#
#4458
#4460
1#
0&
b00000001 '
#4465
0#
#4468
#4470
1#
b00000010 '
#4475
0#
#4478
#4480
1#
b00000011 '
#4485
0#
#4488
#4490
1#
b00000100 '
#4495
0#
#4498
#4500
1#
b01011010 %
1&
b00000000 '
#4505
0#
#4508
#4510
1#
0&
b00000001 '
#4515
0#
#4518
#4520
1#
b00000010 '
#4525
0#
#4528
#4530
1#
b00000011 '
#4535
0#
#4538
#4540
1#
b00000100 '
#4545
0#
#4548
#4550
1#
b01011011 %
1&
b00000000 '
#4555
0#
#4558
#4560
1#
0&
b00000001 '
#4565
0#
#4568
#4570
1#
b00000010 '
#4575
0#
#4578
#4580
1#
b00000011 '
#4585
0#
#4588
#4590
1#
b00000100 '
#4595
0#
#4598
#4600
1#
b01011100 %
1&
b00000000 '
#4605
0#
#4608
#4610
1#
0&
b00000001 '
#4615
0#
#4618
#4620
1#
b00000010 '
#4625
0#
#4628
#4630
1#
b00000011 '
#4635
0#
#4638
#4640
1#
b00000100 '
#4645
0#
#4648
#4650
1#
b01011101 %
1&
b00000000 '
#4655
0#
#4658
#4660
1#
0&
b00000001 '
#4665
0#
#4668
#4670
1#
b00000010 '
#4675
0#
#4678
#4680
1#
b00000011 '
#4685
0#
#4688
#4690
1#
b00000100 '
#4695
0#
#4698
#4700
1#
b01011110 %
1&
b00000000 '
#4705
0#
#4708
#4710
1#
0&
b00000001 '
#4715
0#
#4718
#4720
1#
b00000010 '
#4725
0#
#4728
#4730
1#
b00000011 '
#4735
0#
#4738
#4740
1#
b00000100 '
#4745
0#
#4748
#4750
1#
b01011111 %
1&
b00000000 '
#4755
0#
#4758
#4760
1#
0&
b00000001 '
#4765
0#
#4768
#4770
1#
b00000010 '
#4775
0#
#4778
#4780
1#
b00000011 '
#4785
0#
#4788
#4790
1#
b00000100 '
#4795
0#
#4798
#4800
1#
b01100000 %
1&
b00000000 '
#4805
0#
#4808
#4810
1#
0&
b00000001 '
#4815
0#
#4818
#4820
1#
b00000010 '
#4825
0#
#4828
#4830
1#
b00000011 '
#4835
0#
#4838
#4840
1#
b00000100 '
#4845
0#
#4848
#4850
1#
b01100001 %
1&
b00000000 '
#4855
0#
#4858
#4860
1#
0&
b00000001 '
#4865
0#
#4868
#4870
1#
b00000010 '
#4875
0#
#4878
#4880
1#
b00000011 '
#4885
0#
#4888
#4890
1#
b00000100 '
#4895
0#
#4898
#4900
1#
b01100010 %
1&
b00000000 '
#4905
0#
#4908
#4910
1#
0&
b00000001 '
#4915
0#
#4918
#4920
1#
b00000010 '
#4925
0#
#4928
#4930
1#
b00000011 '
#4935
0#
#4938
#4940
1#
b00000100 '
#4945
0#
#4948
#4950
1#
b01100011 %
1&
b00000000 '
#4955
0#
#4958
#4960
1#
0&
b00000001 '
#4965
0#
#4968
#4970
1#
b00000010 '
#4975
0#
#4978
#4980
1#
b00000011 '
#4985
0#
#4988
#4990
1#
b00000100 '
#4995
0#
#4998
#5000
1#
b01100100 %
1&
b00000000 '
#5005
0#
#5008
#5010
1#
0&
b00000001 '
#5015
0#
#5018
#5020
1#
b00000010 '
#5025
0#
#5028
#5030
1#
b00000011 '
#5035
0#
#5038
#5040
1#
b00000100 '
#5045
0#
#5048
#5050
1#
b01100101 %
1&
b00000000 '
#5055
0#
#5058
#5060
1#
0&
b00000001 '
#5065
0#
#5068
#5070
1#
b00000010 '
#5075
0#
#5078
#5080
1#
b00000011 '
#5085
0#
#5088
#5090
1#
b00000100 '
#5095
0#
#5098
#5100
1#
b01100110 %
1&
b00000000 '
#5105
0#
#5108
#5110
1#
0&
b00000001 '
#5115
0#
#5118
#5120
1#
b00000010 '
#5125
0#
#5128
#5130
1#
b00000011 '
#5135
0#
#5138
#5140
1#
b00000100 '
#5145
0#
#5148
#5150
1#
b01100111 %
1&
b00000000 '
#5155
0#
#5158
#5160
1#
0&
b00000001 '
#5165
0#
#5168
#5170
1#
b00000010 '
#5175
0#
#5178
#5180
1#
b00000011 '
#5185
0#
#5188
#5190
1#
b00000100 '
#5195
0#
#5198
#5200
1#
b01101000 %
1&
b00000000 '
#5205
0#
#5208
#5210
1#
0&
b00000001 '
#5215
0#
#5218
#5220
1#
b00000010 '
#5225
0#
#5228
#5230
1#
b00000011 '
#5235
0#
#5238
#5240
1#
b00000100 '
#5245
0#
#5248
#5250
1#
b01101001 %
1&
b00000000 '
#5255
0#
#5258
#5260
1#
0&
b00000001 '
#5265
0#
#5268
#5270
1#
b00000010 '
#5275
0#
#5278
