tutorial/05_prescaler/prescaler.v
//-- prescaler.v
//-- clk_in: input clock signal
//-- clk_out: output clock signal, lower frequency
module prescaler(input clk_in, output clk_out);
wire clk_in;
wire clk_out;
    
//-- Number of bits of the prescaler (default)
parameter N = 22;
    
//-- Register for implementing the N bit counter
reg [N-1:0] count = 0;
    
//-- The most significant bit goes through the output
assign clk_out = count[N-1];
    
//-- Counter: increases upon a rising edge
always @(posedge(clk_in)) begin
  count <= count + 1;
end
    
endmodule

tutorial/12_mux4/mux4.v
//-- mux4.v
module mux4(input wire clk, output reg [3:0] data);
    
//-- Parametros del secuenciador:
parameter NP = 23;         //-- Bits of the prescaler
parameter VAL0 = 4'b1000;  //-- sequence value 0
parameter VAL1 = 4'b1001;  //-- sequence value 1
parameter VAL2 = 4'b1010;  //-- sequence value 2
parameter VAL3 = 4'b1011;  //-- sequence value 3
    
//-- wires for the 5 inputs to the multiplexer
wire [3:0] val0;
wire [3:0] val1;
wire [3:0] val2;
wire [3:0] val3;
wire [1:0] sel;  //-- 2 bits of selection. 
    
//-- 2 bit counter
reg [1:0] count = 0;
wire clk_pres; //-- output clock of the prescaler 
    
//-- wire the constants to the inputs of the mux. 
assign val0 = VAL0;
assign val1 = VAL1;
assign val2 = VAL2;
assign val3 = VAL3;
    
//-- implement the 4 to 1 multiplexer 
always @*
  case (sel)
     0 : data <= val0;
     1 : data <= val1;
     2 : data <= val2;
     3 : data <= val3;
     default : data <= 0;
  endcase
    
//-- counter to drive the sel wire 
always @(posedge(clk_pres))
  count <= count + 1;
     
//-- drive the sel wire with the counter value
assign sel = count;
    
//-- prescaler that controls the counter frequency
prescaler #(.N(NP))
  PRES (
    .clk_in(clk),
    .clk_out(clk_pres)
  );
    
endmodule

tutorial/12_mux4/mux4_tb.v
module mux4_tb;

    reg clk = 0;

    always  #1 clk = ~clk;

    wire [3:0] data;

    mux4 #(.NP(2))
        mux4_inst(
            .clk(clk),
            .data(data)
        );

    initial
    begin
        $dumpfile("mux4_tb.vcd");
        $dumpvars(0, mux4_tb);

        # 400 $finish;
    end


endmodule

tutorial/12_mux4/mux4_tb.vcd
$date
	Fri Nov 13 10:06:25 2020
$end
$version
	Icarus Verilog
$end
$timescale
	1s
$end
$scope module mux4_tb $end
$var wire 4 ! data [3:0] $end
$var reg 1 " clk $end
$scope module mux4_inst $end
$var wire 1 " clk $end
$var wire 2 # sel [1:0] $end
$var wire 4 $ val0 [3:0] $end
$var wire 4 % val1 [3:0] $end
$var wire 4 & val2 [3:0] $end
$var wire 4 ' val3 [3:0] $end
$var wire 1 ( clk_pres $end
$var reg 2 ) count [1:0] $end
$var reg 4 * data [3:0] $end
$scope module PRES $end
$var wire 1 " clk_in $end
$var wire 1 ( clk_out $end
$var reg 2 + count [1:0] $end
$upscope $end
$upscope $end
$upscope $end
$enddefinitions $end
#0
$dumpvars
b0 +
b1000 *
b0 )
0(
b1011 '
b1010 &
b1001 %
b1000 $
b0 #
0"
b1000 !
$end
#1
b1 +
1"
#2
0"
#3
b1001 !
b1001 *
b1 #
b1 )
1(
b10 +
1"
#4
0"
#5
b11 +
1"
#6
0"
#7
0(
b0 +
1"
#8
0"
#9
b1 +
1"
#10
0"
#11
b1010 !
b1010 *
b10 #
b10 )
1(
b10 +
1"
#12
0"
#13
b11 +
1"
#14
0"
#15
0(
b0 +
1"
#16
0"
#17
b1 +
1"
#18
0"
#19
b1011 !
b1011 *
b11 #
b11 )
1(
b10 +
1"
#20
0"
#21
b11 +
1"
#22
0"
#23
0(
b0 +
1"
#24
0"
#25
b1 +
1"
#26
0"
#27
b1000 !
b1000 *
b0 #
b0 )
1(
b10 +
1"
#28
0"
#29
b11 +
1"
#30
0"
#31
0(
b0 +
1"
#32
0"
#33
b1 +
1"
#34
0"
#35
b1001 !
b1001 *
b1 #
b1 )
1(
b10 +
1"
#36
0"
#37
b11 +
1"
#38
0"
#39
0(
b0 +
1"
#40
0"
#41
b1 +
1"
#42
0"
#43
b1010 !
b1010 *
b10 #
b10 )
1(
b10 +
1"
#44
0"
#45
b11 +
1"
#46
0"
#47
0(
b0 +
1"
#48
0"
#49
b1 +
1"
#50
0"
#51
b1011 !
b1011 *
b11 #
b11 )
1(
b10 +
1"
#52
0"
#53
b11 +
1"
#54
0"
#55
0(
b0 +
1"
#56
0"
#57
b1 +
1"
#58
0"
#59
b1000 !
b1000 *
b0 #
b0 )
1(
b10 +
1"
#60
0"
#61
b11 +
1"
#62
0"
#63
0(
b0 +
1"
#64
0"
#65
b1 +
1"
#66
0"
#67
b1001 !
b1001 *
b1 #
b1 )
1(
b10 +
1"
#68
0"
#69
b11 +
1"
#70
0"
#71
0(
b0 +
1"
#72
0"
#73
b1 +
1"
#74
0"
#75
b1010 !
b1010 *
b10 #
b10 )
1(
b10 +
1"
#76
0"
#77
b11 +
1"
#78
0"
#79
0(
b0 +
1"
#80
0"
#81
b1 +
1"
#82
0"
#83
b1011 !
b1011 *
b11 #
b11 )
1(
b10 +
1"
#84
0"
#85
b11 +
1"
#86
0"
#87
0(
b0 +
1"
#88
0"
#89
b1 +
1"
#90
0"
#91
b1000 !
b1000 *
b0 #
b0 )
1(
b10 +
1"
#92
0"
#93
b11 +
1"
#94
0"
#95
0(
b0 +
1"
#96
0"
#97
b1 +
1"
#98
0"
#99
b1001 !
b1001 *
b1 #
b1 )
1(
b10 +
1"
#100
0"
#101
b11 +
1"
#102
0"
#103
0(
b0 +
1"
#104
0"
#105
b1 +
1"
#106
0"
#107
b1010 !
b1010 *
b10 #
b10 )
1(
b10 +
1"
#108
0"
#109
b11 +
1"
#110
0"
#111
0(
b0 +
1"
#112
0"
#113
b1 +
1"
#114
0"
#115
b1011 !
b1011 *
b11 #
b11 )
1(
b10 +
1"
#116
0"
#117
b11 +
1"
#118
0"
#119
0(
b0 +
1"
#120
0"
#121
b1 +
1"
#122
0"
#123
b1000 !
b1000 *
b0 #
b0 )
1(
b10 +
1"
#124
0"
#125
b11 +
1"
#126
0"
#127
0(
b0 +
1"
#128
0"
#129
b1 +
1"
#130
0"
#131
b1001 !
b1001 *
b1 #
b1 )
1(
b10 +
1"
#132
0"
#133
b11 +
1"
#134
0"
#135
0(
b0 +
1"
#136
0"
#137
b1 +
1"
#138
0"
#139
b1010 !
b1010 *
b10 #
b10 )
1(
b10 +
1"
#140
0"
#141
b11 +
1"
#142
0"
#143
0(
b0 +
1"
#144
0"
#145
b1 +
1"
#146
0"
#147
b1011 !
b1011 *
b11 #
b11 )
1(
b10 +
1"
#148
0"
#149
b11 +
1"
#150
0"
#151
0(
b0 +
1"
#152
0"
#153
b1 +
1"
#154
0"
#155
b1000 !
b1000 *
b0 #
b0 )
1(
b10 +
1"
#156
0"
#157
b11 +
1"
#158
0"
#159
0(
b0 +
1"
#160
0"
#161
b1 +
1"
#162
0"
#163
b1001 !
b1001 *
b1 #
b1 )
1(
b10 +
1"
#164
0"
#165
b11 +
1"
#166
0"
#167
0(
b0 +
1"
#168
0"
#169
b1 +
1"
#170
0"
#171
b1010 !
b1010 *
b10 #
b10 )
1(
b10 +
1"
#172
0"
#173
b11 +
1"
#174
0"
#175
0(
b0 +
1"
#176
0"
#177
b1 +
1"
#178
0"
#179
b1011 !
b1011 *
b11 #
b11 )
1(
b10 +
1"
#180
0"
#181
b11 +
1"
#182
0"
#183
0(
b0 +
1"
#184
0"
#185
b1 +
1"
#186
0"
#187
b1000 !
b1000 *
b0 #
b0 )
1(
b10 +
1"
#188
0"
#189
b11 +
1"
#190
0"
#191
0(
b0 +
1"
#192
0"
#193
b1 +
1"
#194
0"
#195
b1001 !
b1001 *
b1 #
b1 )
1(
b10 +
1"
#196
0"
#197
b11 +
1"
#198
0"
#199
0(
b0 +
1"
#200
0"
#201
b1 +
1"
#202
0"
#203
b1010 !
b1010 *
b10 #
b10 )
1(
b10 +
1"
#204
0"
#205
b11 +
1"
#206
0"
#207
0(
b0 +
1"
#208
0"
#209
b1 +
1"
#210
0"
#211
b1011 !
b1011 *
b11 #
b11 )
1(
b10 +
1"
#212
0"
#213
b11 +
1"
#214
0"
#215
0(
b0 +
1"
#216
0"
#217
b1 +
1"
#218
0"
#219
b1000 !
b1000 *
b0 #
b0 )
1(
b10 +
1"
#220
0"
#221
b11 +
1"
#222
0"
#223
0(
b0 +
1"
#224
0"
#225
b1 +
1"
#226
0"
#227
b1001 !
b1001 *
b1 #
b1 )
1(
b10 +
1"
#228
0"
#229
b11 +
1"
#230
0"
#231
0(
b0 +
1"
#232
0"
#233
b1 +
1"
#234
0"
#235
b1010 !
b1010 *
b10 #
b10 )
1(
b10 +
1"
#236
0"
#237
b11 +
1"
#238
0"
#239
0(
b0 +
1"
#240
0"
#241
b1 +
1"
#242
0"
#243
b1011 !
b1011 *
b11 #
b11 )
1(
b10 +
1"
#244
0"
#245
b11 +
1"
#246
0"
#247
0(
b0 +
1"
#248
0"
#249
b1 +
1"
#250
0"
#251
b1000 !
b1000 *
b0 #
b0 )
1(
b10 +
1"
#252
0"
#253
b11 +
1"
#254
0"
#255
0(
b0 +
1"
#256
0"
#257
b1 +
1"
#258
0"
#259
b1001 !
b1001 *
b1 #
b1 )
1(
b10 +
1"
#260
0"
#261
b11 +
1"
#262
0"
#263
0(
b0 +
1"
#264
0"
#265
b1 +
1"
#266
0"
#267
b1010 !
b1010 *
b10 #
b10 )
1(
b10 +
1"
#268
0"
#269
b11 +
1"
#270
0"
#271
0(
b0 +
1"
#272
0"
#273
b1 +
1"
#274
0"
#275
b1011 !
b1011 *
b11 #
b11 )
1(
b10 +
1"
#276
0"
#277
b11 +
1"
#278
0"
#279
0(
b0 +
1"
#280
0"
#281
b1 +
1"
#282
0"
#283
b1000 !
b1000 *
b0 #
b0 )
1(
b10 +
1"
#284
0"
#285
b11 +
1"
#286
0"
#287
0(
b0 +
1"
#288
0"
#289
b1 +
1"
#290
0"
#291
b1001 !
b1001 *
b1 #
b1 )
1(
b10 +
1"
#292
0"
#293
b11 +
1"
#294
0"
#295
0(
b0 +
1"
#296
0"
#297
b1 +
1"
#298
0"
#299
b1010 !
b1010 *
b10 #
b10 )
1(
b10 +
1"
#300
0"
#301
b11 +
1"
#302
0"
#303
0(
b0 +
1"
#304
0"
#305
b1 +
1"
#306
0"
#307
b1011 !
b1011 *
b11 #
b11 )
1(
b10 +
1"
#308
0"
#309
b11 +
1"
#310
0"
#311
0(
b0 +
1"
#312
0"
#313
b1 +
1"
#314
0"
#315
b1000 !
b1000 *
b0 #
b0 )
1(
b10 +
1"
#316
0"
#317
b11 +
1"
#318
0"
#319
0(
b0 +
1"
#320
0"
#321
b1 +
1"
#322
0"
#323
b1001 !
b1001 *
b1 #
b1 )
1(
b10 +
1"
#324
0"
#325
b11 +
1"
#326
0"
#327
0(
b0 +
1"
#328
0"
#329
b1 +
1"
#330
0"
#331
b1010 !
b1010 *
b10 #
b10 )
1(
b10 +
1"
#332
0"
#333
b11 +
1"
#334
0"
#335
0(
b0 +
1"
#336
0"
#337
b1 +
1"
#338
0"
#339
b1011 !
b1011 *
b11 #
b11 )
1(
b10 +
1"
#340
0"
#341
b11 +
1"
#342
0"
#343
0(
b0 +
1"
#344
0"
#345
b1 +
1"
#346
0"
#347
b1000 !
b1000 *
b0 #
b0 )
1(
b10 +
1"
#348
0"
#349
b11 +
1"
#350
0"
#351
0(
b0 +
1"
#352
0"
#353
b1 +
1"
#354
0"
#355
b1001 !
b1001 *
b1 #
b1 )
1(
b10 +
1"
#356
0"
#357
b11 +
1"
#358
0"
#359
0(
b0 +
1"
#360
0"
#361
b1 +
1"
#362
0"
#363
b1010 !
b1010 *
b10 #
b10 )
1(
b10 +
1"
#364
0"
#365
b11 +
1"
#366
0"
#367
0(
b0 +
1"
#368
0"
#369
b1 +
1"
#370
0"
#371
b1011 !
b1011 *
b11 #
b11 )
1(
b10 +
1"
#372
0"
#373
b11 +
1"
#374
0"
#375
0(
b0 +
1"
#376
0"
#377
b1 +
1"
#378
0"
#379
b1000 !
b1000 *
b0 #
b0 )
1(
b10 +
1"
#380
0"
#381
b11 +
1"
#382
0"
#383
0(
b0 +
1"
#384
0"
#385
b1 +
1"
#386
0"
#387
b1001 !
b1001 *
b1 #
b1 )
1(
b10 +
1"
#388
0"
#389
b11 +
1"
#390
0"
#391
0(
b0 +
1"
#392
0"
#393
b1 +
1"
#394
0"
#395
b1010 !
b1010 *
b10 #
b10 )
1(
b10 +
1"
#396
0"
#397
b11 +
1"
#398
0"
#399
0(
b0 +
1"
